sms/counter/__init__.py
sms/counter/sms_counter.py
sms_counter-0.0.0.dist-info/LICENSE
sms_counter-0.0.0.dist-info/METADATA
sms_counter-0.0.0.dist-info/WHEEL
sms_counter-0.0.0.dist-info/top_level.txt
sms_counter-0.0.0.dist-info/RECORD
