Metadata-Version: 2.1
Name: sms-counter
Version: 0.0.0
Summary: SMS Character Counter
Home-page: https://github.com/Sweego-io/python-sms-counter
Author: Valentin Henon
Author-email: vhenon@mindbaz.com
License: MIT
Classifier: Programming Language :: Python :: 3.9
Requires-Python: >=3.9
License-File: LICENSE
Requires-Dist: pydantic
